uesm/__init__.py
uesm/__main__.py
uesm/cmdline.py
uesm/uepath.py
uesm-0.0.3.dist-info/METADATA
uesm-0.0.3.dist-info/WHEEL
uesm-0.0.3.dist-info/entry_points.txt
uesm-0.0.3.dist-info/top_level.txt
uesm-0.0.3.dist-info/RECORD
