Metadata-Version: 2.1
Name: uesm
Version: 0.0.3
Requires-Python: >=3.9
Requires-Dist: GitPython
Provides-Extra: test
Requires-Dist: pytest ; extra == 'test'
Requires-Dist: pytest-cov ; extra == 'test'
Requires-Dist: GitPython ; extra == 'test'
Requires-Dist: requests-mock ; extra == 'test'
